mailutil.py
__pycache__/mailutil.cpython-38.opt-1.pyc
mailutil-0.4.1.dist-info/LICENSE
mailutil-0.4.1.dist-info/METADATA
mailutil-0.4.1.dist-info/WHEEL
mailutil-0.4.1.dist-info/top_level.txt
mailutil-0.4.1.dist-info/RECORD
